[
  {
    "icon": "material-symbols-light:location-on",
    "title": "Удобное месторасположение",
    "description": "В самом центре города, в шаговой доступности от всех ключевых достопримечательностей."
  },
  {
    "icon": "material-symbols-light:wifi",
    "title": "Бесплатный WiFi",
    "description": "Высокоскоростной интернет доступен на всей территории отеля для работы и отдыха."
  },
  {
    "icon": "material-symbols-light:local-cafe",
    "title": "Бесплатный завтрак",
    "description": "Каждое утро мы предлагаем вкусный континентальный завтрак для всех наших гостей."
  },
  {
    "icon": "material-symbols-light:tv",
    "title": "Кабельное телевидение",
    "description": "Современные телевизоры с широким выбором каналов в каждом номере отеля."
  },
  {
    "icon": "material-symbols-light:local-parking",
    "title": "Бесплатная парковка",
    "description": "Безопасное место для вашего автомобиля рядом с отелем без дополнительной платы."
  },
  {
    "icon": "material-symbols-light:shower",
    "title": "Душевая в каждом номере",
    "description": "Собственная ванная комната с современным душем, феном и косметикой."
  }
]
